sts1_sensors/__init__.py
sts1_sensors/edu/ADXL345.py
sts1_sensors/edu/BME688.py
sts1_sensors/edu/BMM150.py
sts1_sensors/edu/L3GD20H.py
sts1_sensors/edu/TMP112.py
sts1_sensors/edu/__init__.py
sts1_sensors/edu/cam.py
sts1_sensors/nonedu/GUVA_C32.py
sts1_sensors/nonedu/__init__.py
sts1_sensors/nonedu/pysatdosclient.py
sts1_sensors/utils/AbstractSensor.py
sts1_sensors/utils/__init__.py
sts1_sensors/utils/utils.py
sts1_sensors-0.5.2.dist-info/METADATA
sts1_sensors-0.5.2.dist-info/WHEEL
sts1_sensors-0.5.2.dist-info/licenses/LICENSE
sts1_sensors-0.5.2.dist-info/RECORD
