Metadata-Version: 2.4
Name: sts1_sensors
Version: 0.5.2
Summary: A sensor library for the CubeSat STS1 (TU Wien Space Team).
Author-email: Simon Köfinger <simon.koefinger@spaceteam.at>, Florian Rohrer <florian.rohrer@spaceteam.at>
License-File: LICENSE
Requires-Python: >=3.11
Requires-Dist: bme680>=2.0.0
Requires-Dist: smbus2<0.5.0,>=0.4.2
Requires-Dist: structlog>=24.4.0
